data_browser/__init__.py
data_browser/admin.py
data_browser/api.py
data_browser/apps.py
data_browser/common.py
data_browser/format_csv.py
data_browser/helpers.py
data_browser/migration_helpers.py
data_browser/models.py
data_browser/orm_admin.py
data_browser/orm_aggregates.py
data_browser/orm_debug.py
data_browser/orm_fields.py
data_browser/orm_functions.py
data_browser/orm_lookups.py
data_browser/orm_results.py
data_browser/orm_types.py
data_browser/query.py
data_browser/types.py
data_browser/urls.py
data_browser/util.py
data_browser/views.py
data_browser/fe_build/asset-manifest.json
data_browser/fe_build/index.html
data_browser/fe_build/static/css/main.c698af7a.css
data_browser/fe_build/static/css/main.c698af7a.css.map
data_browser/fe_build/static/js/main.c4ca9cb3.js
data_browser/fe_build/static/js/main.c4ca9cb3.js.LICENSE.txt
data_browser/fe_build/static/js/main.c4ca9cb3.js.map
data_browser/migrations/0001_initial.py
data_browser/migrations/0002_auto_20200331_1842.py
data_browser/migrations/0003_remove_view_app.py
data_browser/migrations/0004_auto_20200501_0903.py
data_browser/migrations/0005_auto_20200516_1726.py
data_browser/migrations/0006_auto_20200531_1450.py
data_browser/migrations/0007_view_public_slug.py
data_browser/migrations/0008_view_limit.py
data_browser/migrations/0009_migrate_saved_views.py
data_browser/migrations/0010_shared.py
data_browser/migrations/0011_folder.py
data_browser/migrations/0012_can_share.py
data_browser/migrations/__init__.py
data_browser/templates/data_browser/index.html
data_browser/web_root/android-chrome-192x192.png
data_browser/web_root/android-chrome-512x512.png
data_browser/web_root/apple-touch-icon.png
data_browser/web_root/favicon-16x16.png
data_browser/web_root/favicon-32x32.png
data_browser/web_root/favicon.ico
data_browser/web_root/site.webmanifest
django_data_browser-4.2.10.dist-info/LICENSE
django_data_browser-4.2.10.dist-info/METADATA
django_data_browser-4.2.10.dist-info/WHEEL
django_data_browser-4.2.10.dist-info/top_level.txt
django_data_browser-4.2.10.dist-info/RECORD
