Metadata-Version: 2.1
Name: django-data-browser
Version: 4.2.10
Summary: Interactive user-friendly database explorer.
Home-page: https://github.com/tolomea/django-data-browser
Author: Gordon Wrigley
Author-email: gordon.wrigley@gmail.com
Classifier: Programming Language :: Python :: 3
Classifier: License :: OSI Approved :: MIT License
Classifier: Operating System :: OS Independent
Requires-Python: >=3.8
License-File: LICENSE
Requires-Dist: Django >=3.2
Requires-Dist: hyperlink
Requires-Dist: python-dateutil
Requires-Dist: sqlparse
